Workbook

Sheet Start Here
B2: ShopKart — Excel practice workbook
B3: Data analyst interview prep · Q4 2025 order lines from the fictional ShopKart store
B5: HOW TO USE
B6: 1. Work on the Orders sheet. It is an Excel Table (tblOrders) — add your own columns to the right; formulas fill down automatically.
B7: 2. Products is the product master (tblProducts). You'll need it for Category, product_name and unit_cost.
B8: 3. Go to Tasks. Type each answer in the yellow cell — the Result column tells you if you're right (numbers are checked to 1 decimal place).
B9: 4. Percentages: type 12.3% (or 0.123). Text answers are not case-sensitive.
B10: 5. Stuck? The Answer Key sheet shows one working formula per task (it uses helper columns on Orders_Solved).
B12: DEFINITIONS
B13: Line Revenue = quantity × unit_price − discount (INR)
B14: Valid line = status is Delivered or Shipped (Cancelled / Returned lines earn nothing)
B15: One order can have several lines (rows) — be careful when counting orders vs lines.
... B24: • Use Power Query (Data ▸ Get Data ▸ From Text/CSV) to load data/raw/orders_raw.csv and clean the status / payment_method columns.

Sheet Orders
A1: order_id | B1: order_date | C1: customer_id | D1: city | E1: region | F1: channel | G1: device | H1: payment_method | I1: status | J1: product_id | K1: quantity | L1: unit_price | M1: discount
A2: 509305 | B2: 45931 | C2: 16376 | D2: Mumbai | E2: West | F2: Referral | G2: Mobile App | H2: UPI | I2: Delivered | J2: 112 | K2: 1 | L2: 1574 | M2: 0
A3: 509306 | B3: 45931 | C3: 16561 | D3: Kochi | E3: South | F3: Email | G3: Mobile Web | H3: Credit Card | I3: Cancelled | J3: 119 | K3: 1 | L3: 2309 | M3: 346.35
A4: 509307 | B4: 45931 | C4: 15029 | D4: Noida | E4: North | F4: Organic Search | G4: Desktop | H4: UPI | I4: Delivered | J4: 115 | K4: 1 | L4: 4199 | M4: 0
A5: 509308 | B5: 45931 | C5: 16563 | D5: Lucknow | E5: North | F5: Organic Search | G5: Mobile Web | H5: UPI | I5: Delivered | J5: 104 | K5: 2 | L5: 5249 | M5: 0
A6: 509309 | B6: 45931 | C6: 14305 | D6: Hyderabad | E6: South | F6: Referral | G6: Mobile Web | H6: Credit Card | I6: Delivered | J6: 141 | K6: 1 | L6: 261 | M6: 0
A7: 509309 | B7: 45931 | C7: 14305 | D7: Hyderabad | E7: South | F7: Referral | G7: Mobile Web | H7: Credit Card | I7: Delivered | J7: 119 | K7: 1 | L7: 2309 | M7: 0
A8: 509310 | B8: 45931 | C8: 16572 | D8: Bengaluru | E8: South | F8: Organic Search | G8: Desktop | H8: Net Banking | I8: Delivered | J8: 118 | K8: 1 | L8: 944 | M8: 0
A9: 509311 | B9: 45931 | C9: 14615 | D9: Delhi | E9: North | F9: Organic Search | G9: Mobile App | H9: Net Banking | I9: Delivered | J9: 136 | K9: 2 | L9: 944 | M9: 0
A10: 509311 | B10: 45931 | C10: 14615 | D10: Delhi | E10: North | F10: Organic Search | G10: Mobile App | H10: Net Banking | I10: Delivered | J10: 110 | K10: 1 | L10: 839 | M10: 0
A11: 509312 | B11: 45931 | C11: 16551 | D11: Chandigarh | E11: North | F11: Paid Social | G11: Desktop | H11: UPI | I11: Delivered | J11: 135 | K11: 1 | L11: 1574 | M11: 0
A12: 509312 | B12: 45931 | C12: 16551 | D12: Chandigarh | E12: North | F12: Paid Social | G12: Desktop | H12: UPI | I12: Delivered | J12: 115 | K12: 2 | L12: 4199 | M12: 0
A13: 509313 | B13: 45931 | C13: 16522 | D13: Bengaluru | E13: South | F13: Paid Search | G13: Desktop | H13: UPI | I13: Delivered | J13: 125 | K13: 1 | L13: 1364 | M13: 0
... A4542: 511885 | B4542: 46022 | C4542: 17908 | D4542: Hyderabad | E4542: South | F4542: Paid Social | G4542: Mobile Web | H4542: Cash on Delivery | I4542: Shipped | J4542: 136 | K4542: 1 | L4542: 944 | M4542: 141.6

Sheet Products
A1: product_id | B1: product_name | C1: category | D1: subcategory | E1: list_price | F1: unit_cost
A2: 101 | B2: Wireless Earbuds | C2: Electronics | D2: Audio | E2: 1999 | F2: 1557.99
A3: 102 | B3: Over-Ear Headphones | C3: Electronics | D3: Audio | E3: 3499 | F3: 2688.57
A4: 103 | B4: Bluetooth Speaker | C4: Electronics | D4: Audio | E4: 2499 | F4: 1972.57
A5: 104 | B5: Smartwatch | C5: Electronics | D5: Wearables | E5: 4999 | F5: 3765.09
A6: 105 | B6: Fitness Band | C6: Electronics | D6: Wearables | E6: 2299 | F6: 1795.64
A7: 106 | B7: 20000mAh Power Bank | C7: Electronics | D7: Accessories | E7: 1499 | F7: 1294.15
A8: 107 | B8: 65W Fast Charger | C8: Electronics | D8: Accessories | E8: 1199 | F8: 984.92
A9: 108 | B9: USB-C Cable (2-pack) | C9: Electronics | D9: Accessories | E9: 399 | F9: 303.05
A10: 109 | B10: Mechanical Keyboard | C10: Electronics | D10: Computer | E10: 3999 | F10: 3184.39
A11: 110 | B11: Wireless Mouse | C11: Electronics | D11: Computer | E11: 799 | F11: 657.06
A12: 111 | B12: Cotton T-Shirt | C12: Fashion | D12: Menswear | E12: 499 | F12: 257.44
A13: 112 | B13: Slim Fit Jeans | C13: Fashion | D13: Menswear | E13: 1499 | F13: 810.1
... A49: 148 | B49: Football | C49: Sports | D49: Outdoor | E49: 699 | F49: 425.79

Sheet Tasks
A1: # | B1: Skill | C1: Question | D1: Your answer | E1: Result | F1: expected (hidden) | G1: Hint
A2: 1 | B2: XLOOKUP / VLOOKUP | C2: Add a Category column to the Orders table by looking up product_id in tblProducts. How many order lines are Fashion? | E2: =IF(D2="","",IF(ISNUMBER(D2),IF(ABS(D2-F2)<0.05,"✅ Correct","❌ Try again"),"❌ Not a number")) | F2: 1349 | G2: =XLOOKUP([@product_id], tblProducts[product_id], tblProducts[category]) then COUNTIF
A3: 2 | B3: Calculated column | C3: Add a Line Revenue column = quantity × unit_price − discount. What is the total Line Revenue across ALL lines (any status)? | E3: =IF(D3="","",IF(ISNUMBER(D3),IF(ABS(D3-F3)<0.05,"✅ Correct","❌ Try again"),"❌ Not a number")) | F3: 8039818.8 | G3: =[@quantity]*[@unit_price]-[@discount], then SUM the column
A4: 3 | B4: SUMIFS (OR logic) | C4: Net revenue from VALID lines only (status Delivered or Shipped)? | E4: =IF(D4="","",IF(ISNUMBER(D4),IF(ABS(D4-F4)<0.05,"✅ Correct","❌ Try again"),"❌ Not a number")) | F4: 6820604.8 | G4: SUMIFS can't do OR in one criterion – add two SUMIFS, or SUM(SUMIFS(..., {"Delivered","Shipped"}))
A5: 4 | B5: SUMIFS (multiple criteria) | C5: Valid net revenue from Electronics in the South region? | E5: =IF(D5="","",IF(ISNUMBER(D5),IF(ABS(D5-F5)<0.05,"✅ Correct","❌ Try again"),"❌ Not a number")) | F5: 738239.9 | G5: Three criteria ranges: Category, region, status (x2 statuses)
A6: 5 | B6: COUNTIFS | C6: How many order lines were paid Cash on Delivery AND Cancelled? | E6: =IF(D6="","",IF(ISNUMBER(D6),IF(ABS(D6-F6)<0.05,"✅ Correct","❌ Try again"),"❌ Not a number")) | F6: 104 | G6: COUNTIFS(range1, crit1, range2, crit2)
A7: 6 | B7: Distinct count | C7: How many DISTINCT orders (order_id) are in the sheet? (Lines ≠ orders!) | E7: =IF(D7="","",IF(ISNUMBER(D7),IF(ABS(D7-F7)<0.05,"✅ Correct","❌ Try again"),"❌ Not a number")) | F7: 2581 | G7: Excel 365: =COUNTA(UNIQUE(tblOrders[order_id])). Older: =SUMPRODUCT(1/COUNTIF(rng,rng)) or Remove Duplicates on a copy
A8: 7 | B8: AVERAGEIFS | C8: Average unit_price of Beauty order lines? (2 dp) | E8: =IF(D8="","",IF(ISNUMBER(D8),IF(ABS(D8-F8)<0.05,"✅ Correct","❌ Try again"),"❌ Not a number")) | F8: 601.90448 | G8: AVERAGEIFS(avg_range, criteria_range, criteria)
A9: 8 | B9: MAXIFS | C9: Largest single Line Revenue in Home & Kitchen? | E9: =IF(D9="","",IF(ISNUMBER(D9),IF(ABS(D9-F9)<0.05,"✅ Correct","❌ Try again"),"❌ Not a number")) | F9: 10392 | G9: MAXIFS(max_range, criteria_range, criteria) (Excel 2019+)
A10: 9 | B10: Dates in criteria | C10: Valid net revenue for November 2025? | E10: =IF(D10="","",IF(ISNUMBER(D10),IF(ABS(D10-F10)<0.05,"✅ Correct","❌ Try again"),"❌ Not a number")) | F10: 1655441.2 | G10: Use ">="&DATE(2025,11,1) and "<"&DATE(2025,12,1) as criteria on order_date
A11: 10 | B11: IF | C11: Add an Order Size column: "Large" if Line Revenue ≥ 3000, else "Small". How many lines are Large? | E11: =IF(D11="","",IF(ISNUMBER(D11),IF(ABS(D11-F11)<0.05,"✅ Correct","❌ Try again"),"❌ Not a number")) | F11: 819 | G11: =IF([@[Line Revenue]]>=3000,"Large","Small")
A12: 11 | B12: INDEX / MATCH | C12: What is the product_name of product_id 131? (use INDEX/MATCH on tblProducts) | E12: =IF(D12="","",IF(LOWER(TRIM(D12))=LOWER(F12),"✅ Correct","❌ Try again")) | F12: Face Wash | G12: =INDEX(tblProducts[product_name], MATCH(131, tblProducts[product_id], 0))
A13: 12 | B13: Ratios | C13: Return rate for Fashion = Returned lines ÷ (Delivered + Returned lines). Answer as a % (e.g. 12.3%). | E13: =IF(D13="","",IF(ISNUMBER(D13),IF(OR(ABS(D13-F13)<0.0005,ABS(D13/100-F13)<0.0005),"✅ Correct","❌ Try again"),"❌ Not a number")) | F13: 0.154664 | G13: Two COUNTIFS divided; format as %
A14: 13 | B14: SUMPRODUCT | C14: Gross margin % on valid lines = (revenue − quantity × unit_cost) ÷ revenue. Answer as %. | E14: =IF(D14="","",IF(ISNUMBER(D14),IF(OR(ABS(D14-F14)<0.0005,ABS(D14/100-F14)<0.0005),"✅ Correct","❌ Try again"),"❌ Not a number")) | F14: 0.374871 | G14: Look up unit_cost too, then SUMPRODUCT with a (status="Delivered")+(status="Shipped") mask
A15: 14 | B15: PivotTable | C15: Which city generated the most valid net revenue? (type the city name) | E15: =IF(D15="","",IF(LOWER(TRIM(D15))=LOWER(F15),"✅ Correct","❌ Try again")) | F15: Delhi | G15: Insert ▸ PivotTable: Rows = city, Values = Sum of Line Revenue, Filter = status. Sort descending.
A16: 15 | B16: PivotTable – % of total | C16: What share of valid net revenue came from the Mobile App? Answer as %. | E16: =IF(D16="","",IF(ISNUMBER(D16),IF(OR(ABS(D16-F16)<0.0005,ABS(D16/100-F16)<0.0005),"✅ Correct","❌ Try again"),"❌ Not a number")) | F16: 0.519732 | G16: Pivot: Rows = device, Values = Sum of Line Revenue ▸ Show Values As ▸ % of Grand Total
A17: 16 | B17: Date functions | C17: Total discount given in December 2025 (any status)? | E17: =IF(D17="","",IF(ISNUMBER(D17),IF(ABS(D17-F17)<0.05,"✅ Correct","❌ Try again"),"❌ Not a number")) | F17: 97266.55 | G17: SUMIFS on discount with a date range – or add a Month column with =TEXT([@order_date],"yyyy-mm")
A18: 17 | B18: TEXT / WEEKDAY | C18: Which weekday had the most order lines? (e.g. Monday) | E18: =IF(D18="","",IF(LOWER(TRIM(D18))=LOWER(F18),"✅ Correct","❌ Try again")) | F18: Friday | G18: Add =TEXT([@order_date],"dddd") and pivot / COUNTIF it
A19: 18 | B19: Distinct count with a condition | C19: Average order value of valid orders = valid revenue ÷ number of distinct valid orders? (2 dp) | E19: =IF(D19="","",IF(ISNUMBER(D19),IF(ABS(D19-F19)<0.05,"✅ Correct","❌ Try again"),"❌ Not a number")) | F19: 3077.8903 | G19: Distinct valid orders: =SUMPRODUCT(((status="Delivered")+(status="Shipped"))/COUNTIF(order_id,order_id))
A20: 19 | B20: Distinct count + dates | C20: How many distinct customers placed an order in December 2025? | E20: =IF(D20="","",IF(ISNUMBER(D20),IF(ABS(D20-F20)<0.05,"✅ Correct","❌ Try again"),"❌ Not a number")) | F20: 631 | G20: Excel 365: =COUNTA(UNIQUE(FILTER(customer_id, month="2025-12"))). Older: SUMPRODUCT((month="2025-12")/COUNTIFS(customer_id,customer_id,month,month))
A21: 20 | B21: Average of top N | C21: What is the average Line Revenue of the 10 largest lines (any status)? (2 dp) | E21: =IF(D21="","",IF(ISNUMBER(D21),IF(ABS(D21-F21)<0.05,"✅ Correct","❌ Try again"),"❌ Not a number")) | F21: 12355.645 | G21: =AVERAGE(LARGE(range,{1,2,3,4,5,6,7,8,9,10})) or SORT/TAKE in Excel 365
C23: Score | D23: =COUNTIF(E2:E21,"✅*")&" / 20"

Sheet Orders_Solved
A1: order_id | B1: order_date | C1: customer_id | D1: city | E1: region | F1: channel | G1: device | H1: payment_method | I1: status | J1: product_id | K1: quantity | L1: unit_price | M1: discount | N1: Category | O1: Line Revenue | P1: Month | Q1: Order Size | R1: unit_cost | S1: Weekday #
A2: 509305 | B2: 45931 | C2: 16376 | D2: Mumbai | E2: West | F2: Referral | G2: Mobile App | H2: UPI | I2: Delivered | J2: 112 | K2: 1 | L2: 1574 | M2: 0 | N2: =VLOOKUP(J2,Products!$A$2:$C$49,3,FALSE) | O2: =K2*L2-M2 | P2: =TEXT(B2,"yyyy-mm") | Q2: =IF(O2>=3000,"Large","Small") | R2: =INDEX(Products!$F$2:$F$49,MATCH(J2,Products!$A$2:$A$49,0)) | S2: =WEEKDAY(B2,2)
A3: 509306 | B3: 45931 | C3: 16561 | D3: Kochi | E3: South | F3: Email | G3: Mobile Web | H3: Credit Card | I3: Cancelled | J3: 119 | K3: 1 | L3: 2309 | M3: 346.35 | N3: =VLOOKUP(J3,Products!$A$2:$C$49,3,FALSE) | O3: =K3*L3-M3 | P3: =TEXT(B3,"yyyy-mm") | Q3: =IF(O3>=3000,"Large","Small") | R3: =INDEX(Products!$F$2:$F$49,MATCH(J3,Products!$A$2:$A$49,0)) | S3: =WEEKDAY(B3,2)
A4: 509307 | B4: 45931 | C4: 15029 | D4: Noida | E4: North | F4: Organic Search | G4: Desktop | H4: UPI | I4: Delivered | J4: 115 | K4: 1 | L4: 4199 | M4: 0 | N4: =VLOOKUP(J4,Products!$A$2:$C$49,3,FALSE) | O4: =K4*L4-M4 | P4: =TEXT(B4,"yyyy-mm") | Q4: =IF(O4>=3000,"Large","Small") | R4: =INDEX(Products!$F$2:$F$49,MATCH(J4,Products!$A$2:$A$49,0)) | S4: =WEEKDAY(B4,2)
A5: 509308 | B5: 45931 | C5: 16563 | D5: Lucknow | E5: North | F5: Organic Search | G5: Mobile Web | H5: UPI | I5: Delivered | J5: 104 | K5: 2 | L5: 5249 | M5: 0 | N5: =VLOOKUP(J5,Products!$A$2:$C$49,3,FALSE) | O5: =K5*L5-M5 | P5: =TEXT(B5,"yyyy-mm") | Q5: =IF(O5>=3000,"Large","Small") | R5: =INDEX(Products!$F$2:$F$49,MATCH(J5,Products!$A$2:$A$49,0)) | S5: =WEEKDAY(B5,2)
A6: 509309 | B6: 45931 | C6: 14305 | D6: Hyderabad | E6: South | F6: Referral | G6: Mobile Web | H6: Credit Card | I6: Delivered | J6: 141 | K6: 1 | L6: 261 | M6: 0 | N6: =VLOOKUP(J6,Products!$A$2:$C$49,3,FALSE) | O6: =K6*L6-M6 | P6: =TEXT(B6,"yyyy-mm") | Q6: =IF(O6>=3000,"Large","Small") | R6: =INDEX(Products!$F$2:$F$49,MATCH(J6,Products!$A$2:$A$49,0)) | S6: =WEEKDAY(B6,2)
A7: 509309 | B7: 45931 | C7: 14305 | D7: Hyderabad | E7: South | F7: Referral | G7: Mobile Web | H7: Credit Card | I7: Delivered | J7: 119 | K7: 1 | L7: 2309 | M7: 0 | N7: =VLOOKUP(J7,Products!$A$2:$C$49,3,FALSE) | O7: =K7*L7-M7 | P7: =TEXT(B7,"yyyy-mm") | Q7: =IF(O7>=3000,"Large","Small") | R7: =INDEX(Products!$F$2:$F$49,MATCH(J7,Products!$A$2:$A$49,0)) | S7: =WEEKDAY(B7,2)
A8: 509310 | B8: 45931 | C8: 16572 | D8: Bengaluru | E8: South | F8: Organic Search | G8: Desktop | H8: Net Banking | I8: Delivered | J8: 118 | K8: 1 | L8: 944 | M8: 0 | N8: =VLOOKUP(J8,Products!$A$2:$C$49,3,FALSE) | O8: =K8*L8-M8 | P8: =TEXT(B8,"yyyy-mm") | Q8: =IF(O8>=3000,"Large","Small") | R8: =INDEX(Products!$F$2:$F$49,MATCH(J8,Products!$A$2:$A$49,0)) | S8: =WEEKDAY(B8,2)
A9: 509311 | B9: 45931 | C9: 14615 | D9: Delhi | E9: North | F9: Organic Search | G9: Mobile App | H9: Net Banking | I9: Delivered | J9: 136 | K9: 2 | L9: 944 | M9: 0 | N9: =VLOOKUP(J9,Products!$A$2:$C$49,3,FALSE) | O9: =K9*L9-M9 | P9: =TEXT(B9,"yyyy-mm") | Q9: =IF(O9>=3000,"Large","Small") | R9: =INDEX(Products!$F$2:$F$49,MATCH(J9,Products!$A$2:$A$49,0)) | S9: =WEEKDAY(B9,2)
A10: 509311 | B10: 45931 | C10: 14615 | D10: Delhi | E10: North | F10: Organic Search | G10: Mobile App | H10: Net Banking | I10: Delivered | J10: 110 | K10: 1 | L10: 839 | M10: 0 | N10: =VLOOKUP(J10,Products!$A$2:$C$49,3,FALSE) | O10: =K10*L10-M10 | P10: =TEXT(B10,"yyyy-mm") | Q10: =IF(O10>=3000,"Large","Small") | R10: =INDEX(Products!$F$2:$F$49,MATCH(J10,Products!$A$2:$A$49,0)) | S10: =WEEKDAY(B10,2)
A11: 509312 | B11: 45931 | C11: 16551 | D11: Chandigarh | E11: North | F11: Paid Social | G11: Desktop | H11: UPI | I11: Delivered | J11: 135 | K11: 1 | L11: 1574 | M11: 0 | N11: =VLOOKUP(J11,Products!$A$2:$C$49,3,FALSE) | O11: =K11*L11-M11 | P11: =TEXT(B11,"yyyy-mm") | Q11: =IF(O11>=3000,"Large","Small") | R11: =INDEX(Products!$F$2:$F$49,MATCH(J11,Products!$A$2:$A$49,0)) | S11: =WEEKDAY(B11,2)
A12: 509312 | B12: 45931 | C12: 16551 | D12: Chandigarh | E12: North | F12: Paid Social | G12: Desktop | H12: UPI | I12: Delivered | J12: 115 | K12: 2 | L12: 4199 | M12: 0 | N12: =VLOOKUP(J12,Products!$A$2:$C$49,3,FALSE) | O12: =K12*L12-M12 | P12: =TEXT(B12,"yyyy-mm") | Q12: =IF(O12>=3000,"Large","Small") | R12: =INDEX(Products!$F$2:$F$49,MATCH(J12,Products!$A$2:$A$49,0)) | S12: =WEEKDAY(B12,2)
A13: 509313 | B13: 45931 | C13: 16522 | D13: Bengaluru | E13: South | F13: Paid Search | G13: Desktop | H13: UPI | I13: Delivered | J13: 125 | K13: 1 | L13: 1364 | M13: 0 | N13: =VLOOKUP(J13,Products!$A$2:$C$49,3,FALSE) | O13: =K13*L13-M13 | P13: =TEXT(B13,"yyyy-mm") | Q13: =IF(O13>=3000,"Large","Small") | R13: =INDEX(Products!$F$2:$F$49,MATCH(J13,Products!$A$2:$A$49,0)) | S13: =WEEKDAY(B13,2)
... A4542: 511885 | B4542: 46022 | C4542: 17908 | D4542: Hyderabad | E4542: South | F4542: Paid Social | G4542: Mobile Web | H4542: Cash on Delivery | I4542: Shipped | J4542: 136 | K4542: 1 | L4542: 944 | M4542: 141.6 | N4542: =VLOOKUP(J4542,Products!$A$2:$C$49,3,FALSE) | O4542: =K4542*L4542-M4542 | P4542: =TEXT(B4542,"yyyy-mm") | Q4542: =IF(O4542>=3000,"Large","Small") | R4542: =INDEX(Products!$F$2:$F$49,MATCH(J4542,Products!$A$2:$A$49,0)) | S4542: =WEEKDAY(B4542,2)

Sheet Answer Key
A1: Answer Key — one working approach per task (formulas point at Orders_Solved)
A3: # | B3: Formula result | C3: Formula used (see cell B) | H3: city | I3: valid revenue | K3: weekday | L3: order lines
A4: 1 | B4: =COUNTIF(Orders_Solved!$N$2:$N$4542,"Fashion") | C4: =COUNTIF($N$2:$N$4542,"Fashion") | H4: Ahmedabad | I4: =SUMIFS(Orders_Solved!$O$2:$O$4542,Orders_Solved!$D$2:$D$4542,H4,Orders_Solved!$I$2:$I$4542,"Delivered")+SUMIFS(Orders_Solved!$O$2:$O$4542,Orders_Solved!$D$2:$D$4542,H4,Orders_Solved!$I$2:$I$4542,"Shipped") | K4: Monday | L4: =COUNTIF(Orders_Solved!$S$2:$S$4542,1)
A5: 2 | B5: =SUM(Orders_Solved!$O$2:$O$4542) | C5: =SUM($O$2:$O$4542) | H5: Bengaluru | I5: =SUMIFS(Orders_Solved!$O$2:$O$4542,Orders_Solved!$D$2:$D$4542,H5,Orders_Solved!$I$2:$I$4542,"Delivered")+SUMIFS(Orders_Solved!$O$2:$O$4542,Orders_Solved!$D$2:$D$4542,H5,Orders_Solved!$I$2:$I$4542,"Shipped") | K5: Tuesday | L5: =COUNTIF(Orders_Solved!$S$2:$S$4542,2)
A6: 3 | B6: =SUMIFS(Orders_Solved!$O$2:$O$4542,Orders_Solved!$I$2:$I$4542,"Delivered")+SUMIFS(Orders_Solved!$O$2:$O$4542,Orders_Solved!$I$2:$I$4542,"Shipped") | C6: =SUMIFS($O$2:$O$4542,$I$2:$I$4542,"Delivered")+SUMIFS($O$2:$O$4542,$I$2:$I$4542,"Shipped") | H6: Chandigarh | I6: =SUMIFS(Orders_Solved!$O$2:$O$4542,Orders_Solved!$D$2:$D$4542,H6,Orders_Solved!$I$2:$I$4542,"Delivered")+SUMIFS(Orders_Solved!$O$2:$O$4542,Orders_Solved!$D$2:$D$4542,H6,Orders_Solved!$I$2:$I$4542,"Shipped") | K6: Wednesday | L6: =COUNTIF(Orders_Solved!$S$2:$S$4542,3)
A7: 4 | B7: =SUMIFS(Orders_Solved!$O$2:$O$4542,Orders_Solved!$N$2:$N$4542,"Electronics",Orders_Solved!$E$2:$E$4542,"South",Orders_Solved!$I$2:$I$4542,"Delivered")+SUMIFS(Orders_Solved!$O$2:$O$4542,Orders_Solved!$N$2:$N$4542,"Electronics",Orders_Solved!$E$2:$E$4542,"South",Orders_Solved!$I$2:$I$4542,"Shipped") | C7: =SUMIFS($O$2:$O$4542,$N$2:$N$4542,"Electronics",$E$2:$E$4542,"South",$I$2:$I$4542,"Delivered")+SUMIFS($O$2:$O$4542,$N$2:$N$4542,"Electronics",$E$2:$E$4542,"South",$I$2:$I$4542,"Shipped") | H7: Chennai | I7: =SUMIFS(Orders_Solved!$O$2:$O$4542,Orders_Solved!$D$2:$D$4542,H7,Orders_Solved!$I$2:$I$4542,"Delivered")+SUMIFS(Orders_Solved!$O$2:$O$4542,Orders_Solved!$D$2:$D$4542,H7,Orders_Solved!$I$2:$I$4542,"Shipped") | K7: Thursday | L7: =COUNTIF(Orders_Solved!$S$2:$S$4542,4)
A8: 5 | B8: =COUNTIFS(Orders_Solved!$H$2:$H$4542,"Cash on Delivery",Orders_Solved!$I$2:$I$4542,"Cancelled") | C8: =COUNTIFS($H$2:$H$4542,"Cash on Delivery",$I$2:$I$4542,"Cancelled") | H8: Delhi | I8: =SUMIFS(Orders_Solved!$O$2:$O$4542,Orders_Solved!$D$2:$D$4542,H8,Orders_Solved!$I$2:$I$4542,"Delivered")+SUMIFS(Orders_Solved!$O$2:$O$4542,Orders_Solved!$D$2:$D$4542,H8,Orders_Solved!$I$2:$I$4542,"Shipped") | K8: Friday | L8: =COUNTIF(Orders_Solved!$S$2:$S$4542,5)
A9: 6 | B9: =SUMPRODUCT(1/COUNTIF(Orders_Solved!$A$2:$A$4542,Orders_Solved!$A$2:$A$4542)) | C9: =SUMPRODUCT(1/COUNTIF($A$2:$A$4542,$A$2:$A$4542)) | H9: Gurugram | I9: =SUMIFS(Orders_Solved!$O$2:$O$4542,Orders_Solved!$D$2:$D$4542,H9,Orders_Solved!$I$2:$I$4542,"Delivered")+SUMIFS(Orders_Solved!$O$2:$O$4542,Orders_Solved!$D$2:$D$4542,H9,Orders_Solved!$I$2:$I$4542,"Shipped") | K9: Saturday | L9: =COUNTIF(Orders_Solved!$S$2:$S$4542,6)
A10: 7 | B10: =AVERAGEIFS(Orders_Solved!$L$2:$L$4542,Orders_Solved!$N$2:$N$4542,"Beauty") | C10: =AVERAGEIFS($L$2:$L$4542,$N$2:$N$4542,"Beauty") | H10: Hyderabad | I10: =SUMIFS(Orders_Solved!$O$2:$O$4542,Orders_Solved!$D$2:$D$4542,H10,Orders_Solved!$I$2:$I$4542,"Delivered")+SUMIFS(Orders_Solved!$O$2:$O$4542,Orders_Solved!$D$2:$D$4542,H10,Orders_Solved!$I$2:$I$4542,"Shipped") | K10: Sunday | L10: =COUNTIF(Orders_Solved!$S$2:$S$4542,7)
A11: 8 | B11: =MAXIFS(Orders_Solved!$O$2:$O$4542,Orders_Solved!$N$2:$N$4542,"Home & Kitchen") | C11: =MAXIFS($O$2:$O$4542,$N$2:$N$4542,"Home & Kitchen") | H11: Indore | I11: =SUMIFS(Orders_Solved!$O$2:$O$4542,Orders_Solved!$D$2:$D$4542,H11,Orders_Solved!$I$2:$I$4542,"Delivered")+SUMIFS(Orders_Solved!$O$2:$O$4542,Orders_Solved!$D$2:$D$4542,H11,Orders_Solved!$I$2:$I$4542,"Shipped")
A12: 9 | B12: =SUMIFS(Orders_Solved!$O$2:$O$4542,Orders_Solved!$B$2:$B$4542,">="&DATE(2025,11,1),Orders_Solved!$B$2:$B$4542,"<"&DATE(2025,12,1),Orders_Solved!$I$2:$I$4542,"Delivered")+SUMIFS(Orders_Solved!$O$2:$O$4542,Orders_Solved!$B$2:$B$4542,">="&DATE(2025,11,1),Orders_Solved!$B$2:$B$4542,"<"&DATE(2025,12,1),Orders_Solved!$I$2:$I$4542,"Shipped") | C12: =SUMIFS($O$2:$O$4542,$B$2:$B$4542,">="&DATE(2025,11,1),$B$2:$B$4542,"<"&DATE(2025,12,1),$I$2:$I$4542,"Delivered")+SUMIFS($O$2:$O$4542,$B$2:$B$4542,">="&DATE(2025,11,1),$B$2:$B$4542,"<"&DATE(2025,12,1),$I$2:$I$4542,"Shipped") | H12: Jaipur | I12: =SUMIFS(Orders_Solved!$O$2:$O$4542,Orders_Solved!$D$2:$D$4542,H12,Orders_Solved!$I$2:$I$4542,"Delivered")+SUMIFS(Orders_Solved!$O$2:$O$4542,Orders_Solved!$D$2:$D$4542,H12,Orders_Solved!$I$2:$I$4542,"Shipped")
A13: 10 | B13: =COUNTIF(Orders_Solved!$Q$2:$Q$4542,"Large") | C13: =COUNTIF($Q$2:$Q$4542,"Large") | H13: Kochi | I13: =SUMIFS(Orders_Solved!$O$2:$O$4542,Orders_Solved!$D$2:$D$4542,H13,Orders_Solved!$I$2:$I$4542,"Delivered")+SUMIFS(Orders_Solved!$O$2:$O$4542,Orders_Solved!$D$2:$D$4542,H13,Orders_Solved!$I$2:$I$4542,"Shipped")
A14: 11 | B14: =INDEX(Products!$B$2:$B$49,MATCH(131,Products!$A$2:$A$49,0)) | C14: =INDEX(Products!$B$2:$B$49,MATCH(131,Products!$A$2:$A$49,0)) | H14: Kolkata | I14: =SUMIFS(Orders_Solved!$O$2:$O$4542,Orders_Solved!$D$2:$D$4542,H14,Orders_Solved!$I$2:$I$4542,"Delivered")+SUMIFS(Orders_Solved!$O$2:$O$4542,Orders_Solved!$D$2:$D$4542,H14,Orders_Solved!$I$2:$I$4542,"Shipped")
A15: 12 | B15: =COUNTIFS(Orders_Solved!$N$2:$N$4542,"Fashion",Orders_Solved!$I$2:$I$4542,"Returned")/(COUNTIFS(Orders_Solved!$N$2:$N$4542,"Fashion",Orders_Solved!$I$2:$I$4542,"Returned")+COUNTIFS(Orders_Solved!$N$2:$N$4542,"Fashion",Orders_Solved!$I$2:$I$4542,"Delivered")) | C15: =COUNTIFS($N$2:$N$4542,"Fashion",$I$2:$I$4542,"Returned")/(COUNTIFS($N$2:$N$4542,"Fashion",$I$2:$I$4542,"Returned")+COUNTIFS($N$2:$N$4542,"Fashion",$I$2:$I$4542,"Delivered")) | H15: Lucknow | I15: =SUMIFS(Orders_Solved!$O$2:$O$4542,Orders_Solved!$D$2:$D$4542,H15,Orders_Solved!$I$2:$I$4542,"Delivered")+SUMIFS(Orders_Solved!$O$2:$O$4542,Orders_Solved!$D$2:$D$4542,H15,Orders_Solved!$I$2:$I$4542,"Shipped")
A16: 13 | B16: =(SUMPRODUCT(Orders_Solved!$O$2:$O$4542,(Orders_Solved!$I$2:$I$4542="Delivered")+(Orders_Solved!$I$2:$I$4542="Shipped"))-SUMPRODUCT(Orders_Solved!$K$2:$K$4542,Orders_Solved!$R$2:$R$4542,(Orders_Solved!$I$2:$I$4542="Delivered")+(Orders_Solved!$I$2:$I$4542="Shipped")))/SUMPRODUCT(Orders_Solved!$O$2:$O$4542,(Orders_Solved!$I$2:$I$4542="Delivered")+(Orders_Solved!$I$2:$I$4542="Shipped")) | C16: =(SUMPRODUCT($O$2:$O$4542,($I$2:$I$4542="Delivered")+($I$2:$I$4542="Shipped"))-SUMPRODUCT($K$2:$K$4542,$R$2:$R$4542,($I$2:$I$4542="Delivered")+($I$2:$I$4542="Shipped")))/SUMPRODUCT($O$2:$O$4542,($I$2:$I$4542="Delivered")+($I$2:$I$4542="Shipped")) | H16: Mumbai | I16: =SUMIFS(Orders_Solved!$O$2:$O$4542,Orders_Solved!$D$2:$D$4542,H16,Orders_Solved!$I$2:$I$4542,"Delivered")+SUMIFS(Orders_Solved!$O$2:$O$4542,Orders_Solved!$D$2:$D$4542,H16,Orders_Solved!$I$2:$I$4542,"Shipped")
A17: 14 | B17: =INDEX('Answer Key'!$H$4:$H$18,MATCH(MAX('Answer Key'!$I$4:$I$18),'Answer Key'!$I$4:$I$18,0)) | C17: =INDEX('Answer Key'!$H$4:$H$18,MATCH(MAX('Answer Key'!$I$4:$I$18),'Answer Key'!$I$4:$I$18,0)) | H17: Noida | I17: =SUMIFS(Orders_Solved!$O$2:$O$4542,Orders_Solved!$D$2:$D$4542,H17,Orders_Solved!$I$2:$I$4542,"Delivered")+SUMIFS(Orders_Solved!$O$2:$O$4542,Orders_Solved!$D$2:$D$4542,H17,Orders_Solved!$I$2:$I$4542,"Shipped")
A18: 15 | B18: =(SUMIFS(Orders_Solved!$O$2:$O$4542,Orders_Solved!$G$2:$G$4542,"Mobile App",Orders_Solved!$I$2:$I$4542,"Delivered")+SUMIFS(Orders_Solved!$O$2:$O$4542,Orders_Solved!$G$2:$G$4542,"Mobile App",Orders_Solved!$I$2:$I$4542,"Shipped"))/(SUMIFS(Orders_Solved!$O$2:$O$4542,Orders_Solved!$I$2:$I$4542,"Delivered")+SUMIFS(Orders_Solved!$O$2:$O$4542,Orders_Solved!$I$2:$I$4542,"Shipped")) | C18: =(SUMIFS($O$2:$O$4542,$G$2:$G$4542,"Mobile App",$I$2:$I$4542,"Delivered")+SUMIFS($O$2:$O$4542,$G$2:$G$4542,"Mobile App",$I$2:$I$4542,"Shipped"))/(SUMIFS($O$2:$O$4542,$I$2:$I$4542,"Delivered")+SUMIFS($O$2:$O$4542,$I$2:$I$4542,"Shipped")) | H18: Pune | I18: =SUMIFS(Orders_Solved!$O$2:$O$4542,Orders_Solved!$D$2:$D$4542,H18,Orders_Solved!$I$2:$I$4542,"Delivered")+SUMIFS(Orders_Solved!$O$2:$O$4542,Orders_Solved!$D$2:$D$4542,H18,Orders_Solved!$I$2:$I$4542,"Shipped")
A19: 16 | B19: =SUMIFS(Orders_Solved!$M$2:$M$4542,Orders_Solved!$P$2:$P$4542,"2025-12") | C19: =SUMIFS($M$2:$M$4542,$P$2:$P$4542,"2025-12")
A20: 17 | B20: =INDEX('Answer Key'!$K$4:$K$10,MATCH(MAX('Answer Key'!$L$4:$L$10),'Answer Key'!$L$4:$L$10,0)) | C20: =INDEX('Answer Key'!$K$4:$K$10,MATCH(MAX('Answer Key'!$L$4:$L$10),'Answer Key'!$L$4:$L$10,0))
A21: 18 | B21: =(SUMIFS(Orders_Solved!$O$2:$O$4542,Orders_Solved!$I$2:$I$4542,"Delivered")+SUMIFS(Orders_Solved!$O$2:$O$4542,Orders_Solved!$I$2:$I$4542,"Shipped"))/SUMPRODUCT(((Orders_Solved!$I$2:$I$4542="Delivered")+(Orders_Solved!$I$2:$I$4542="Shipped"))/COUNTIF(Orders_Solved!$A$2:$A$4542,Orders_Solved!$A$2:$A$4542)) | C21: =(SUMIFS($O$2:$O$4542,$I$2:$I$4542,"Delivered")+SUMIFS($O$2:$O$4542,$I$2:$I$4542,"Shipped"))/SUMPRODUCT((($I$2:$I$4542="Delivered")+($I$2:$I$4542="Shipped"))/COUNTIF($A$2:$A$4542,$A$2:$A$4542))
A22: 19 | B22: =SUMPRODUCT((Orders_Solved!$P$2:$P$4542="2025-12")/COUNTIFS(Orders_Solved!$C$2:$C$4542,Orders_Solved!$C$2:$C$4542,Orders_Solved!$P$2:$P$4542,Orders_Solved!$P$2:$P$4542)) | C22: =SUMPRODUCT(($P$2:$P$4542="2025-12")/COUNTIFS($C$2:$C$4542,$C$2:$C$4542,$P$2:$P$4542,$P$2:$P$4542))
A23: 20 | B23: =SUMPRODUCT(LARGE(Orders_Solved!$O$2:$O$4542,ROW($1:$10)))/10 | C23: =SUMPRODUCT(LARGE($O$2:$O$4542,ROW($1:$10)))/10
